microdata_tools/__init__.py
microdata_tools/packaging/__init__.py
microdata_tools/packaging/_decrypt.py
microdata_tools/packaging/_encrypt.py
microdata_tools/packaging/_utils.py
microdata_tools/packaging/exceptions/__init__.py
microdata_tools/validation/__init__.py
microdata_tools/validation/adapter/local_storage.py
microdata_tools/validation/components/temporal_attributes.py
microdata_tools/validation/components/unit_id_types.py
microdata_tools/validation/components/unit_type_variables/BEDRIFT.json
microdata_tools/validation/components/unit_type_variables/BK_HELSESTASJONSKONSULTASJON.json
microdata_tools/validation/components/unit_type_variables/FAMILIE.json
microdata_tools/validation/components/unit_type_variables/FENGSLINGER_TILGANG.json
microdata_tools/validation/components/unit_type_variables/FORETAK.json
microdata_tools/validation/components/unit_type_variables/HKDIR_HYU_OPPMELDING.json
microdata_tools/validation/components/unit_type_variables/HKDIR_STUDIESOKNAD.json
microdata_tools/validation/components/unit_type_variables/HUSHOLDNING.json
microdata_tools/validation/components/unit_type_variables/JOBB.json
microdata_tools/validation/components/unit_type_variables/KJORETOY.json
microdata_tools/validation/components/unit_type_variables/KOMMUNE.json
microdata_tools/validation/components/unit_type_variables/KRG_KREFTTILFELLE.json
microdata_tools/validation/components/unit_type_variables/KURS.json
microdata_tools/validation/components/unit_type_variables/MALEPUNKT.json
microdata_tools/validation/components/unit_type_variables/NPR_EPISODE.json
microdata_tools/validation/components/unit_type_variables/NPR_SYKEHUSOPPHOLD.json
microdata_tools/validation/components/unit_type_variables/PERSON.json
microdata_tools/validation/components/unit_type_variables/SOESKEN.json
microdata_tools/validation/components/unit_type_variables/SOSTIL.json
microdata_tools/validation/components/unit_type_variables/TRAFIKKULYKKE.json
microdata_tools-1.10.4.dist-info/METADATA
microdata_tools-1.10.4.dist-info/WHEEL
microdata_tools-1.10.4.dist-info/licenses/LICENSE.md
microdata_tools-1.10.4.dist-info/RECORD
