Metadata-Version: 2.4
Name: microdata-tools
Version: 1.10.4
Summary: Tools for the microdata.no platform
Author: microdata-developers
License: MIT
License-File: LICENSE.md
Requires-Python: <4.0,>=3.9
Requires-Dist: cryptography<44.0.0,>=43.0.0; python_version <= '3.10'
Requires-Dist: cryptography>=44.0.0; python_version > '3.10'
Requires-Dist: numpy<2.1,>=2.0; python_version == '3.9'
Requires-Dist: numpy>=2.2.0; python_version >= '3.10'
Requires-Dist: pyarrow>=21.0.0
Requires-Dist: pydantic>=2.11.7
